LICENSE
MANIFEST.in
README.rst
setup.py
doc/analytics_reference.rst
doc/analytics_usage.rst
doc/changelog.rst
doc/hacking.rst
doc/hacking_reference.rst
doc/index.rst
doc/install.rst
doc/plugins_reference.rst
doc/tracking_reference.rst
doc/tracking_usage.rst
piwikapi/__init__.py
piwikapi/analytics.py
piwikapi/exceptions.py
piwikapi/tracking.py
piwikapi.egg-info/PKG-INFO
piwikapi.egg-info/SOURCES.txt
piwikapi.egg-info/dependency_links.txt
piwikapi.egg-info/top_level.txt
piwikapi.egg-info/zip-safe