Metadata-Version: 1.1
Name: piwikapi
Version: 0.2.1
Summary: Python Piwik API
Home-page: http://github.com/nkuttler/python-piwikapi
Author: Nicolas Kuttler
Author-email: pypi@nicolaskuttler.com
License: BSD
Platform: UNKNOWN
Classifier: Development Status :: 3 - Alpha
Classifier: Environment :: Web Environment
Classifier: Intended Audience :: Developers
Classifier: License :: OSI Approved :: BSD License
Classifier: Operating System :: OS Independent
Classifier: Programming Language :: Python
